NScat/__init__.py
NScat/code.py
NScat/query.py
NScat-0.0.5.dist-info/METADATA
NScat-0.0.5.dist-info/WHEEL
NScat-0.0.5.dist-info/top_level.txt
NScat-0.0.5.dist-info/RECORD
