Metadata-Version: 2.1
Name: NScat
Version: 0.0.5
Summary: A package python to query various neutron star parameters from publicly available databases
Home-page: https://nscat.readthedocs.io/en/latest/
Author: Rohit Chinchwadkar, Satyajit ,Chakraborty, Shreetama Pradhan, Aishwarya Panja and Sushan Konar
Author-email: chinchwadkarrohit4@gmail.com
License: MIT
Platform: UNKNOWN
Requires-Dist: rich (>=10.10.0)
